meshagent/markitdown/__init__.py
meshagent/markitdown/version.py
meshagent/markitdown/tools/__init__.py
meshagent/markitdown/tools/markitdown.py
meshagent_markitdown-0.25.1.dist-info/licenses/LICENSE
meshagent_markitdown-0.25.1.dist-info/METADATA
meshagent_markitdown-0.25.1.dist-info/WHEEL
meshagent_markitdown-0.25.1.dist-info/top_level.txt
meshagent_markitdown-0.25.1.dist-info/RECORD
