Metadata-Version: 2.4
Name: meshagent-markitdown
Version: 0.25.1
Summary: Markitdown support for Meshagent
License-Expression: Apache-2.0
Project-URL: Documentation, https://docs.meshagent.com
Project-URL: Website, https://www.meshagent.com
Project-URL: Source, https://www.meshagent.com
Requires-Python: >=3.13
License-File: LICENSE
Requires-Dist: pytest~=8.4
Requires-Dist: pytest-asyncio~=0.26
Requires-Dist: meshagent-api~=0.25.1
Requires-Dist: openapi-core~=0.19
Requires-Dist: markitdown[docx,outlook,pdf,pptx,xlsx]~=0.1
Dynamic: license-file
